Metadata-Version: 1.1
Name: somtime
Version: 1.0.8
Summary: Python implementation of Self Organizing Map with capability to use Dynamic Time Warping (DTW) as a distance measure.
Home-page: https://github.com/ali-javed/somtime
Author: A. Javed
Author-email: alijaved@live.com
License: UNKNOWN
Download-URL: https://github.com/ali-javed/somtime/archive/1.0.8.tar.gz
Platform: UNKNOWN
